cubicweb_expense/__init__.py
cubicweb_expense/__pkginfo__.py
cubicweb_expense/entities.py
cubicweb_expense/schema.py
cubicweb_expense/site_cubicweb.py
cubicweb_expense/sobjects.py
cubicweb_expense/views.py
cubicweb_expense/data/cubes.expense.css
cubicweb_expense/data/cubes.expense.js
cubicweb_expense/data/logilab.png
cubicweb_expense/i18n/en.po
cubicweb_expense/i18n/fr.po
cubicweb_expense/migration/0.10.0_Any.py
cubicweb_expense/migration/0.2.0_Any.py
cubicweb_expense/migration/0.2.3_Any.py
cubicweb_expense/migration/0.2.4_Any.py
cubicweb_expense/migration/0.4.4_Any.py
cubicweb_expense/migration/0.6.0_Any.py
cubicweb_expense/migration/0.7.0_Any.py
cubicweb_expense/migration/postcreate.py
cubicweb_expense/pdfgen/__init__.py
cubicweb_expense/pdfgen/flowgenerators.py
cubicweb_expense/pdfgen/styles.py
cubicweb_expense/pdfgen/templates.py
cubicweb_expense/pdfgen/utils.py
cubicweb_expense/pdfgen/writers.py
cubicweb_expense-1.1.0.dist-info/METADATA
cubicweb_expense-1.1.0.dist-info/WHEEL
cubicweb_expense-1.1.0.dist-info/entry_points.txt
cubicweb_expense-1.1.0.dist-info/top_level.txt
cubicweb_expense-1.1.0.dist-info/RECORD
